.gitignore
AUTHORS
LICENSE
MANIFEST.in
README.md
setup.py
django_outputs.egg-info/PKG-INFO
django_outputs.egg-info/SOURCES.txt
django_outputs.egg-info/dependency_links.txt
django_outputs.egg-info/requires.txt
django_outputs.egg-info/top_level.txt
outputs/__init__.py
outputs/admin.py
outputs/apps.py
outputs/cron.py
outputs/filters.py
outputs/forms.py
outputs/jobs.py
outputs/mixins.py
outputs/models.py
outputs/querysets.py
outputs/settings.py
outputs/signal_tasks.py
outputs/signals.py
outputs/urls.py
outputs/views.py
outputs/widgets.py
outputs/migrations/0001_initial.py
outputs/migrations/0002_auto_20200821_1321.py
outputs/migrations/0003_init_emails.py
outputs/migrations/0004_auto_20200824_1418.py
outputs/migrations/0005_change_column_type.py
outputs/migrations/0006_auto_20200910_2149.py
outputs/migrations/0007_auto_20220208_1958.py
outputs/migrations/0008_auto_20230111_1350.py
outputs/migrations/0009_auto_20230111_1353.py
outputs/migrations/0010_set_exporter_path.py
outputs/migrations/0011_reformat_export_fields_permissions.py
outputs/migrations/0012_auto_20230125_1252.py
outputs/migrations/0013_auto_20230125_1259.py
outputs/migrations/0014_local_timezone_reschedule_schedulers.py
outputs/migrations/0015_auto_20230206_1905.py
outputs/migrations/__init__.py
outputs/templates/outputs/export_confirmation.html
outputs/templates/outputs/export_message_body.html
outputs/templates/outputs/export_selection.html
outputs/templates/outputs/export_table.html
outputs/templates/outputs/scheduler_detail.html
outputs/templates/outputs/scheduler_form.html
outputs/templates/outputs/scheduler_table.html
outputs/templates/outputs/helpers/scheduler_header.html
outputs/templates/outputs/widgets/custom_checkbox_select.html
outputs/templates/outputs/widgets/export_fields_permissions_layout.html
outputs/templates/outputs/widgets/export_fields_permissions_widget.html
outputs/templates/outputs/widgets/exports.html
outputs/templates/outputs/widgets/legend.html
outputs/templates/outputs/widgets/schedulers.html