Metadata-Version: 2.1
Name: django-outputs
Version: 2.1.5
Summary: Exports and schedulers for Django
Home-page: https://github.com/PragmaticMates/django-outputs
Author: Pragmatic Mates
Author-email: info@pragmaticmates.com
Maintainer: Pragmatic Mates
Maintainer-email: info@pragmaticmates.com
License: GPLv3
Keywords: django outputs export scheduler rq redis
Platform: UNKNOWN
Classifier: Programming Language :: Python :: 3.5
Classifier: Programming Language :: Python :: 3.6
Classifier: Operating System :: OS Independent
Classifier: Environment :: Web Environment
Classifier: Intended Audience :: Developers
Classifier: Framework :: Django
Classifier: License :: OSI Approved :: BSD License
Classifier: Development Status :: 3 - Alpha
License-File: LICENSE
License-File: AUTHORS
